{"get":"fixtures\/players","parameters":{"fixture":"710755"},"errors":[],"results":2,"paging":{"current":1,"total":1},"response":[{"team":{"id":38,"name":"Watford","logo":"https:\/\/media.api-sports.io\/football\/teams\/38.png","update":"2022-05-24T04:12:40+00:00"},"players":[{"player":{"id":44775,"name":"Daniel Bachmann","photo":"https:\/\/media.api-sports.io\/football\/players\/44775.png"},"statistics":[{"games":{"minutes":90,"number":26,"position":"G","rating":"5.5","captain":false,"substitute":false},"offsides":null,"shots":{"total":null,"on":null},"goals":{"total":null,"conceded":4,"assists":null,"saves":2},"passes":{"total":23,"key":null,"accuracy":"13"},"tackles":{"total":null,"blocks":null,"interceptions":null},"duels":{"total":1,"won":null},"dribbles":{"attempts":null,"success":null,"past":null},"fouls":{"drawn":null,"committed":1},"cards":{"yellow":0,"red":0},"penalty":{"won":null,"commited":1,"scored":0,"missed":0,"saved":0}}]},{"player":{"id":18794,"name":"Kiko Femen\u00eda","photo":"https:\/\/media.api-sports.io\/football\/players\/18794.png"},"statistics":[{"games":{"minutes":40,"number":21,"position":"D","rating":"6.2","captain":false,"substitute":false},"offsides":null,"shots":{"total":null,"on":null},"goals":{"total":null,"conceded":0,"assists":null,"saves":null},"passes":{"total":15,"key":null,"accuracy":"9"},"tackles":{"total":null,"blocks":null,"interceptions":1},"duels":{"total":1,"won":1},"dribbles":{"attempts":null,"success":null,"past":null},"fouls":{"drawn":1,"committed":null},"cards":{"yellow":0,"red":0},"penalty":{"won":null,"commited":null,"scored":0,"missed":0,"saved":null}}]},{"player":{"id":31016,"name":"Francisco Sierralta","photo":"https:\/\/media.api-sports.io\/football\/players\/31016.png"},"statistics":[{"games":{"minutes":90,"number":31,"position":"D","rating":"6.7","captain":false,"substitute":false},"offsides":null,"shots":{"total":1,"on":1},"goals":{"total":null,"conceded":0,"assists":null,"saves":null},"passes":{"total":32,"key":null,"accuracy":"14"},"tackles":{"total":2,"blocks":1,"interceptions":3},"duels":{"total":17,"won":13},"dribbles":{"attempts":null,"success":null,"past":1},"fouls":{"drawn":2,"committed":2},"cards":{"yellow":0,"red":0},"penalty":{"won":null,"commited":null,"scored":0,"missed":0,"saved":null}}]},{"player":{"id":18793,"name":"Craig Cathcart","photo":"https:\/\/media.api-sports.io\/football\/players\/18793.png"},"statistics":[{"games":{"minutes":90,"number":15,"position":"D","rating":"6.5","captain":false,"substitute":false},"offsides":null,"shots":{"total":null,"on":null},"goals":{"total":null,"conceded":0,"assists":null,"saves":null},"passes":{"total":27,"key":null,"accuracy":"23"},"tackles":{"total":1,"blocks":2,"interceptions":1},"duels":{"total":3,"won":1},"dribbles":{"attempts":null,"success":null,"past":null},"fouls":{"drawn":null,"committed":null},"cards":{"yellow":0,"red":0},"penalty":{"won":null,"commited":null,"scored":0,"missed":0,"saved":null}}]},{"player":{"id":18799,"name":"Adam Masina","photo":"https:\/\/media.api-sports.io\/football\/players\/18799.png"},"statistics":[{"games":{"minutes":90,"number":11,"position":"D","rating":"5.9","captain":false,"substitute":false},"offsides":null,"shots":{"total":1,"on":null},"goals":{"total":null,"conceded":0,"assists":null,"saves":null},"passes":{"total":26,"key":null,"accuracy":"13"},"tackles":{"total":1,"blocks":1,"interceptions":1},"duels":{"total":8,"won":3},"dribbles":{"attempts":null,"success":null,"past":2},"fouls":{"drawn":null,"committed":1},"cards":{"yellow":0,"red":0},"penalty":{"won":null,"commited":null,"scored":0,"missed":0,"saved":null}}]},{"player":{"id":179,"name":"Moussa Sissoko","photo":"https:\/\/media.api-sports.io\/football\/players\/179.png"},"statistics":[{"games":{"minutes":90,"number":19,"position":"M","rating":"6.3","captain":true,"substitute":false},"offsides":null,"shots":{"total":1,"on":1},"goals":{"total":null,"conceded":0,"assists":null,"saves":null},"passes":{"total":25,"key":1,"accuracy":"17"},"tackles":{"total":1,"blocks":null,"interceptions":2},"duels":{"total":10,"won":4},"dribbles":{"attempts":2,"success":1,"past":1},"fouls":{"drawn":null,"committed":1},"cards":{"yellow":0,"red":0},"penalty":{"won":null,"commited":null,"scored":0,"missed":0,"saved":null}}]},{"player":{"id":47582,"name":"Cucho Hern\u00e1ndez","photo":"https:\/\/media.api-sports.io\/football\/players\/47582.png"},"statistics":[{"games":{"minutes":45,"number":29,"position":"M","rating":"6.3","captain":false,"substitute":false},"offsides":null,"shots":{"total":1,"on":null},"goals":{"total":null,"conceded":0,"assists":null,"saves":null},"passes":{"total":20,"key":null,"accuracy":"11"},"tackles":{"total":1,"blocks":null,"interceptions":null},"duels":{"total":8,"won":4},"dribbles":{"attempts":null,"success":null,"past":null},"fouls":{"drawn":1,"committed":null},"cards":{"yellow":0,"red":0},"penalty":{"won":null,"commited":null,"scored":0,"missed":0,"saved":null}}]},{"player":{"id":31023,"name":"Juraj Kucka","photo":"https:\/\/media.api-sports.io\/football\/players\/31023.png"},"statistics":[{"games":{"minutes":90,"number":33,"position":"M","rating":"7.2","captain":false,"substitute":false},"offsides":null,"shots":{"total":1,"on":null},"goals":{"total":null,"conceded":0,"assists":null,"saves":null},"passes":{"total":45,"key":1,"accuracy":"34"},"tackles":{"total":4,"blocks":null,"interceptions":2},"duels":{"total":19,"won":12},"dribbles":{"attempts":1,"success":1,"past":3},"fouls":{"drawn":3,"committed":2},"cards":{"yellow":0,"red":0},"penalty":{"won":null,"commited":null,"scored":0,"missed":0,"saved":null}}]},{"player":{"id":49942,"name":"Ozan Tufan","photo":"https:\/\/media.api-sports.io\/football\/players\/49942.png"},"statistics":[{"games":{"minutes":62,"number":18,"position":"M","rating":"6.2","captain":false,"substitute":false},"offsides":null,"shots":{"total":null,"on":null},"goals":{"total":null,"conceded":0,"assists":null,"saves":null},"passes":{"total":16,"key":null,"accuracy":"11"},"tackles":{"total":null,"blocks":null,"interceptions":null},"duels":{"total":4,"won":2},"dribbles":{"attempts":1,"success":1,"past":null},"fouls":{"drawn":null,"committed":2},"cards":{"yellow":0,"red":0},"penalty":{"won":null,"commited":null,"scored":0,"missed":0,"saved":null}}]},{"player":{"id":18881,"name":"Joshua King","photo":"https:\/\/media.api-sports.io\/football\/players\/18881.png"},"statistics":[{"games":{"minutes":90,"number":7,"position":"M","rating":"6.9","captain":false,"substitute":false},"offsides":null,"shots":{"total":2,"on":1},"goals":{"total":null,"conceded":0,"assists":1,"saves":null},"passes":{"total":24,"key":1,"accuracy":"16"},"tackles":{"total":3,"blocks":null,"interceptions":1},"duels":{"total":20,"won":12},"dribbles":{"attempts":5,"success":3,"past":1},"fouls":{"drawn":1,"committed":1},"cards":{"yellow":0,"red":0},"penalty":{"won":null,"commited":null,"scored":0,"missed":0,"saved":null}}]},{"player":{"id":80,"name":"Emmanuel Dennis","photo":"https:\/\/media.api-sports.io\/football\/players\/80.png"},"statistics":[{"games":{"minutes":90,"number":25,"position":"F","rating":"6.9","captain":false,"substitute":false},"offsides":null,"shots":{"total":2,"on":2},"goals":{"total":1,"conceded":0,"assists":null,"saves":null},"passes":{"total":17,"key":null,"accuracy":"11"},"tackles":{"total":2,"blocks":null,"interceptions":null},"duels":{"total":13,"won":5},"dribbles":{"attempts":3,"success":1,"past":null},"fouls":{"drawn":2,"committed":null},"cards":{"yellow":0,"red":0},"penalty":{"won":null,"commited":null,"scored":0,"missed":0,"saved":null}}]},{"player":{"id":349288,"name":"Vincent Angelini","photo":"https:\/\/media.api-sports.io\/football\/players\/349288.png"},"statistics":[{"games":{"minutes":null,"number":41,"position":"G","rating":null,"captain":false,"substitute":true},"offsides":null,"shots":{"total":null,"on":null},"goals":{"total":null,"conceded":0,"assists":null,"saves":null},"passes":{"total":null,"key":null,"accuracy":null},"tackles":{"total":null,"blocks":null,"interceptions":null},"duels":{"total":null,"won":null},"dribbles":{"attempts":null,"success":null,"past":null},"fouls":{"drawn":null,"committed":null},"cards":{"yellow":0,"red":0},"penalty":{"won":null,"commited":null,"scored":0,"missed":0,"saved":null}}]},{"player":{"id":21100,"name":"Imr\u00e2n Louza","photo":"https:\/\/media.api-sports.io\/football\/players\/21100.png"},"statistics":[{"games":{"minutes":50,"number":6,"position":"M","rating":"7.2","captain":false,"substitute":true},"offsides":null,"shots":{"total":null,"on":null},"goals":{"total":null,"conceded":0,"assists":null,"saves":null},"passes":{"total":33,"key":2,"accuracy":"27"},"tackles":{"total":1,"blocks":null,"interceptions":2},"duels":{"total":3,"won":1},"dribbles":{"attempts":1,"success":null,"past":null},"fouls":{"drawn":null,"committed":null},"cards":{"yellow":0,"red":0},"penalty":{"won":null,"commited":null,"scored":0,"missed":0,"saved":null}}]},{"player":{"id":18874,"name":"Dan Gosling","photo":"https:\/\/media.api-sports.io\/football\/players\/18874.png"},"statistics":[{"games":{"minutes":null,"number":16,"position":"M","rating":null,"captain":false,"substitute":true},"offsides":null,"shots":{"total":null,"on":null},"goals":{"total":null,"conceded":0,"assists":null,"saves":null},"passes":{"total":null,"key":null,"accuracy":null},"tackles":{"total":null,"blocks":null,"interceptions":null},"duels":{"total":null,"won":null},"dribbles":{"attempts":null,"success":null,"past":null},"fouls":{"drawn":null,"committed":null},"cards":{"yellow":0,"red":0},"penalty":{"won":null,"commited":null,"scored":0,"missed":0,"saved":null}}]},{"player":{"id":167660,"name":"James Morris","photo":"https:\/\/media.api-sports.io\/football\/players\/167660.png"},"statistics":[{"games":{"minutes":null,"number":42,"position":"D","rating":null,"captain":false,"substitute":true},"offsides":null,"shots":{"total":null,"on":null},"goals":{"total":null,"conceded":0,"assists":null,"saves":null},"passes":{"total":null,"key":null,"accuracy":null},"tackles":{"total":null,"blocks":null,"interceptions":null},"duels":{"total":null,"won":null},"dribbles":{"attempts":null,"success":null,"past":null},"fouls":{"drawn":null,"committed":null},"cards":{"yellow":0,"red":0},"penalty":{"won":null,"commited":null,"scored":0,"missed":0,"saved":null}}]},{"player":{"id":350318,"name":"Kamil Conteh","photo":"https:\/\/media.api-sports.io\/football\/players\/350318.png"},"statistics":[{"games":{"minutes":null,"number":45,"position":"M","rating":null,"captain":false,"substitute":true},"offsides":null,"shots":{"total":null,"on":null},"goals":{"total":null,"conceded":0,"assists":null,"saves":null},"passes":{"total":null,"key":null,"accuracy":null},"tackles":{"total":null,"blocks":null,"interceptions":null},"duels":{"total":null,"won":null},"dribbles":{"attempts":null,"success":null,"past":null},"fouls":{"drawn":null,"committed":null},"cards":{"yellow":0,"red":0},"penalty":{"won":null,"commited":null,"scored":0,"missed":0,"saved":null}}]},{"player":{"id":2860,"name":"Ken Sema","photo":"https:\/\/media.api-sports.io\/football\/players\/2860.png"},"statistics":[{"games":{"minutes":28,"number":12,"position":"M","rating":"6","captain":false,"substitute":true},"offsides":null,"shots":{"total":null,"on":null},"goals":{"total":null,"conceded":0,"assists":null,"saves":null},"passes":{"total":2,"key":null,"accuracy":"1"},"tackles":{"total":null,"blocks":null,"interceptions":null},"duels":{"total":4,"won":null},"dribbles":{"attempts":1,"success":null,"past":1},"fouls":{"drawn":null,"committed":1},"cards":{"yellow":0,"red":0},"penalty":{"won":null,"commited":null,"scored":0,"missed":0,"saved":null}}]},{"player":{"id":19251,"name":"Ashley Fletcher","photo":"https:\/\/media.api-sports.io\/football\/players\/19251.png"},"statistics":[{"games":{"minutes":null,"number":17,"position":"F","rating":null,"captain":false,"substitute":true},"offsides":null,"shots":{"total":null,"on":null},"goals":{"total":null,"conceded":0,"assists":null,"saves":null},"passes":{"total":null,"key":null,"accuracy":null},"tackles":{"total":null,"blocks":null,"interceptions":null},"duels":{"total":null,"won":null},"dribbles":{"attempts":null,"success":null,"past":null},"fouls":{"drawn":null,"committed":null},"cards":{"yellow":0,"red":0},"penalty":{"won":null,"commited":null,"scored":0,"missed":0,"saved":null}}]},{"player":{"id":10329,"name":"Jo\u00e3o Pedro","photo":"https:\/\/media.api-sports.io\/football\/players\/10329.png"},"statistics":[{"games":{"minutes":45,"number":10,"position":"F","rating":"7.6","captain":false,"substitute":true},"offsides":null,"shots":{"total":1,"on":null},"goals":{"total":null,"conceded":0,"assists":null,"saves":null},"passes":{"total":11,"key":3,"accuracy":"9"},"tackles":{"total":null,"blocks":null,"interceptions":null},"duels":{"total":7,"won":5},"dribbles":{"attempts":4,"success":4,"past":null},"fouls":{"drawn":1,"committed":1},"cards":{"yellow":0,"red":0},"penalty":{"won":null,"commited":null,"scored":0,"missed":0,"saved":null}}]}]},{"team":{"id":48,"name":"West Ham","logo":"https:\/\/media.api-sports.io\/football\/teams\/48.png","update":"2022-05-24T04:12:40+00:00"},"players":[{"player":{"id":2997,"name":"\u0141ukasz Fabia\u0144ski","photo":"https:\/\/media.api-sports.io\/football\/players\/2997.png"},"statistics":[{"games":{"minutes":90,"number":1,"position":"G","rating":"7.3","captain":false,"substitute":false},"offsides":null,"shots":{"total":null,"on":null},"goals":{"total":null,"conceded":1,"assists":null,"saves":4},"passes":{"total":24,"key":null,"accuracy":"9"},"tackles":{"total":null,"blocks":null,"interceptions":null},"duels":{"total":null,"won":null},"dribbles":{"attempts":null,"success":null,"past":null},"fouls":{"drawn":null,"committed":null},"cards":{"yellow":0,"red":0},"penalty":{"won":null,"commited":null,"scored":0,"missed":0,"saved":0}}]},{"player":{"id":1231,"name":"Vladim\u00edr Coufal","photo":"https:\/\/media.api-sports.io\/football\/players\/1231.png"},"statistics":[{"games":{"minutes":90,"number":5,"position":"D","rating":"6.6","captain":false,"substitute":false},"offsides":null,"shots":{"total":null,"on":null},"goals":{"total":null,"conceded":0,"assists":null,"saves":null},"passes":{"total":38,"key":null,"accuracy":"29"},"tackles":{"total":2,"blocks":null,"interceptions":3},"duels":{"total":10,"won":4},"dribbles":{"attempts":2,"success":1,"past":3},"fouls":{"drawn":1,"committed":null},"cards":{"yellow":0,"red":0},"penalty":{"won":null,"commited":null,"scored":0,"missed":0,"saved":null}}]},{"player":{"id":19147,"name":"Craig Dawson","photo":"https:\/\/media.api-sports.io\/football\/players\/19147.png"},"statistics":[{"games":{"minutes":90,"number":15,"position":"D","rating":"6.6","captain":false,"substitute":false},"offsides":null,"shots":{"total":null,"on":null},"goals":{"total":null,"conceded":0,"assists":null,"saves":null},"passes":{"total":28,"key":null,"accuracy":"20"},"tackles":{"total":null,"blocks":3,"interceptions":1},"duels":{"total":11,"won":4},"dribbles":{"attempts":null,"success":null,"past":null},"fouls":{"drawn":null,"committed":3},"cards":{"yellow":1,"red":0},"penalty":{"won":null,"commited":null,"scored":0,"missed":0,"saved":null}}]},{"player":{"id":18814,"name":"Issa Diop","photo":"https:\/\/media.api-sports.io\/football\/players\/18814.png"},"statistics":[{"games":{"minutes":90,"number":23,"position":"D","rating":"6.6","captain":false,"substitute":false},"offsides":null,"shots":{"total":null,"on":null},"goals":{"total":null,"conceded":0,"assists":null,"saves":null},"passes":{"total":47,"key":null,"accuracy":"38"},"tackles":{"total":1,"blocks":null,"interceptions":3},"duels":{"total":5,"won":2},"dribbles":{"attempts":null,"success":null,"past":null},"fouls":{"drawn":1,"committed":1},"cards":{"yellow":0,"red":0},"penalty":{"won":null,"commited":null,"scored":0,"missed":0,"saved":null}}]},{"player":{"id":18823,"name":"Ben Johnson","photo":"https:\/\/media.api-sports.io\/football\/players\/18823.png"},"statistics":[{"games":{"minutes":82,"number":31,"position":"D","rating":"6.2","captain":false,"substitute":false},"offsides":null,"shots":{"total":null,"on":null},"goals":{"total":null,"conceded":0,"assists":null,"saves":null},"passes":{"total":35,"key":null,"accuracy":"23"},"tackles":{"total":2,"blocks":null,"interceptions":1},"duels":{"total":11,"won":3},"dribbles":{"attempts":null,"success":null,"past":1},"fouls":{"drawn":null,"committed":1},"cards":{"yellow":0,"red":0},"penalty":{"won":null,"commited":null,"scored":0,"missed":0,"saved":null}}]},{"player":{"id":18826,"name":"Mark Noble","photo":"https:\/\/media.api-sports.io\/football\/players\/18826.png"},"statistics":[{"games":{"minutes":90,"number":16,"position":"M","rating":"6.5","captain":true,"substitute":false},"offsides":null,"shots":{"total":1,"on":1},"goals":{"total":1,"conceded":0,"assists":null,"saves":null},"passes":{"total":68,"key":null,"accuracy":"52"},"tackles":{"total":null,"blocks":null,"interceptions":1},"duels":{"total":5,"won":2},"dribbles":{"attempts":1,"success":null,"past":2},"fouls":{"drawn":2,"committed":null},"cards":{"yellow":0,"red":0},"penalty":{"won":null,"commited":null,"scored":1,"missed":0,"saved":null}}]},{"player":{"id":1243,"name":"Tom\u00e1\u0161 Sou\u010dek","photo":"https:\/\/media.api-sports.io\/football\/players\/1243.png"},"statistics":[{"games":{"minutes":90,"number":28,"position":"M","rating":"8.2","captain":false,"substitute":false},"offsides":null,"shots":{"total":2,"on":1},"goals":{"total":1,"conceded":0,"assists":null,"saves":null},"passes":{"total":55,"key":1,"accuracy":"42"},"tackles":{"total":5,"blocks":null,"interceptions":2},"duels":{"total":20,"won":12},"dribbles":{"attempts":null,"success":null,"past":2},"fouls":{"drawn":1,"committed":2},"cards":{"yellow":0,"red":0},"penalty":{"won":null,"commited":null,"scored":0,"missed":0,"saved":null}}]},{"player":{"id":19428,"name":"Jarrod Bowen","photo":"https:\/\/media.api-sports.io\/football\/players\/19428.png"},"statistics":[{"games":{"minutes":90,"number":20,"position":"M","rating":"8.3","captain":false,"substitute":false},"offsides":null,"shots":{"total":1,"on":1},"goals":{"total":null,"conceded":0,"assists":2,"saves":null},"passes":{"total":30,"key":3,"accuracy":"21"},"tackles":{"total":1,"blocks":null,"interceptions":null},"duels":{"total":14,"won":8},"dribbles":{"attempts":5,"success":4,"past":1},"fouls":{"drawn":1,"committed":null},"cards":{"yellow":0,"red":0},"penalty":{"won":1,"commited":null,"scored":0,"missed":0,"saved":null}}]},{"player":{"id":2473,"name":"Manuel Lanzini","photo":"https:\/\/media.api-sports.io\/football\/players\/2473.png"},"statistics":[{"games":{"minutes":89,"number":10,"position":"M","rating":"7.3","captain":false,"substitute":false},"offsides":null,"shots":{"total":null,"on":null},"goals":{"total":null,"conceded":0,"assists":null,"saves":null},"passes":{"total":47,"key":3,"accuracy":"43"},"tackles":{"total":2,"blocks":null,"interceptions":1},"duels":{"total":5,"won":5},"dribbles":{"attempts":2,"success":2,"past":null},"fouls":{"drawn":1,"committed":1},"cards":{"yellow":0,"red":0},"penalty":{"won":null,"commited":null,"scored":0,"missed":0,"saved":null}}]},{"player":{"id":19361,"name":"Sa\u00efd Benrahma","photo":"https:\/\/media.api-sports.io\/football\/players\/19361.png"},"statistics":[{"games":{"minutes":85,"number":22,"position":"M","rating":"7.2","captain":false,"substitute":false},"offsides":1,"shots":{"total":2,"on":1},"goals":{"total":1,"conceded":0,"assists":null,"saves":null},"passes":{"total":22,"key":2,"accuracy":"17"},"tackles":{"total":null,"blocks":null,"interceptions":2},"duels":{"total":7,"won":2},"dribbles":{"attempts":3,"success":1,"past":null},"fouls":{"drawn":1,"committed":null},"cards":{"yellow":0,"red":0},"penalty":{"won":null,"commited":null,"scored":0,"missed":0,"saved":null}}]},{"player":{"id":18819,"name":"Michail Antonio","photo":"https:\/\/media.api-sports.io\/football\/players\/18819.png"},"statistics":[{"games":{"minutes":90,"number":9,"position":"F","rating":"6.9","captain":false,"substitute":false},"offsides":null,"shots":{"total":2,"on":1},"goals":{"total":null,"conceded":0,"assists":1,"saves":null},"passes":{"total":18,"key":2,"accuracy":"15"},"tackles":{"total":null,"blocks":null,"interceptions":null},"duels":{"total":21,"won":9},"dribbles":{"attempts":2,"success":1,"past":1},"fouls":{"drawn":3,"committed":3},"cards":{"yellow":0,"red":0},"penalty":{"won":null,"commited":null,"scored":0,"missed":0,"saved":null}}]},{"player":{"id":253,"name":"Alphonse Ar\u00e9ola","photo":"https:\/\/media.api-sports.io\/football\/players\/253.png"},"statistics":[{"games":{"minutes":null,"number":13,"position":"G","rating":null,"captain":false,"substitute":true},"offsides":null,"shots":{"total":null,"on":null},"goals":{"total":null,"conceded":0,"assists":null,"saves":null},"passes":{"total":null,"key":null,"accuracy":null},"tackles":{"total":null,"blocks":null,"interceptions":null},"duels":{"total":null,"won":null},"dribbles":{"attempts":null,"success":null,"past":null},"fouls":{"drawn":null,"committed":null},"cards":{"yellow":0,"red":0},"penalty":{"won":null,"commited":null,"scored":0,"missed":0,"saved":null}}]},{"player":{"id":141133,"name":"Ajibola-Joshua Alese","photo":"https:\/\/media.api-sports.io\/football\/players\/141133.png"},"statistics":[{"games":{"minutes":null,"number":42,"position":"D","rating":null,"captain":false,"substitute":true},"offsides":null,"shots":{"total":null,"on":null},"goals":{"total":null,"conceded":0,"assists":null,"saves":null},"passes":{"total":null,"key":null,"accuracy":null},"tackles":{"total":null,"blocks":null,"interceptions":null},"duels":{"total":null,"won":null},"dribbles":{"attempts":null,"success":null,"past":null},"fouls":{"drawn":null,"committed":null},"cards":{"yellow":0,"red":0},"penalty":{"won":null,"commited":null,"scored":0,"missed":0,"saved":null}}]},{"player":{"id":18815,"name":"Ryan Fredericks","photo":"https:\/\/media.api-sports.io\/football\/players\/18815.png"},"statistics":[{"games":{"minutes":null,"number":24,"position":"D","rating":null,"captain":false,"substitute":true},"offsides":null,"shots":{"total":null,"on":null},"goals":{"total":null,"conceded":0,"assists":null,"saves":null},"passes":{"total":null,"key":null,"accuracy":null},"tackles":{"total":null,"blocks":null,"interceptions":null},"duels":{"total":null,"won":null},"dribbles":{"attempts":null,"success":null,"past":null},"fouls":{"drawn":null,"committed":null},"cards":{"yellow":0,"red":0},"penalty":{"won":null,"commited":null,"scored":0,"missed":0,"saved":null}}]},{"player":{"id":171058,"name":"Harrison Ashby","photo":"https:\/\/media.api-sports.io\/football\/players\/171058.png"},"statistics":[{"games":{"minutes":null,"number":50,"position":"D","rating":null,"captain":false,"substitute":true},"offsides":null,"shots":{"total":null,"on":null},"goals":{"total":null,"conceded":0,"assists":null,"saves":null},"passes":{"total":null,"key":null,"accuracy":null},"tackles":{"total":null,"blocks":null,"interceptions":null},"duels":{"total":null,"won":null},"dribbles":{"attempts":null,"success":null,"past":null},"fouls":{"drawn":null,"committed":null},"cards":{"yellow":0,"red":0},"penalty":{"won":null,"commited":null,"scored":0,"missed":0,"saved":null}}]},{"player":{"id":842,"name":"Nikola Vla\u0161i\u0107","photo":"https:\/\/media.api-sports.io\/football\/players\/842.png"},"statistics":[{"games":{"minutes":11,"number":11,"position":"M","rating":"7","captain":false,"substitute":true},"offsides":null,"shots":{"total":1,"on":1},"goals":{"total":1,"conceded":0,"assists":null,"saves":null},"passes":{"total":4,"key":null,"accuracy":"3"},"tackles":{"total":null,"blocks":null,"interceptions":1},"duels":{"total":5,"won":1},"dribbles":{"attempts":2,"success":null,"past":1},"fouls":{"drawn":1,"committed":1},"cards":{"yellow":0,"red":0},"penalty":{"won":null,"commited":null,"scored":0,"missed":0,"saved":null}}]},{"player":{"id":18816,"name":"Arthur Masuaku","photo":"https:\/\/media.api-sports.io\/football\/players\/18816.png"},"statistics":[{"games":{"minutes":8,"number":26,"position":"D","rating":"7.2","captain":false,"substitute":true},"offsides":null,"shots":{"total":null,"on":null},"goals":{"total":null,"conceded":0,"assists":null,"saves":null},"passes":{"total":5,"key":null,"accuracy":"4"},"tackles":{"total":2,"blocks":null,"interceptions":1},"duels":{"total":2,"won":2},"dribbles":{"attempts":null,"success":null,"past":null},"fouls":{"drawn":null,"committed":null},"cards":{"yellow":0,"red":0},"penalty":{"won":null,"commited":null,"scored":0,"missed":0,"saved":null}}]},{"player":{"id":1234,"name":"Alex Kr\u00e1l","photo":"https:\/\/media.api-sports.io\/football\/players\/1234.png"},"statistics":[{"games":{"minutes":1,"number":33,"position":"M","rating":null,"captain":false,"substitute":true},"offsides":null,"shots":{"total":null,"on":null},"goals":{"total":null,"conceded":0,"assists":null,"saves":null},"passes":{"total":2,"key":null,"accuracy":null},"tackles":{"total":null,"blocks":null,"interceptions":null},"duels":{"total":2,"won":1},"dribbles":{"attempts":null,"success":null,"past":null},"fouls":{"drawn":null,"committed":null},"cards":{"yellow":0,"red":0},"penalty":{"won":null,"commited":null,"scored":0,"missed":0,"saved":null}}]},{"player":{"id":1131,"name":"Armstrong Oko-Flex","photo":"https:\/\/media.api-sports.io\/football\/players\/1131.png"},"statistics":[{"games":{"minutes":null,"number":40,"position":"F","rating":null,"captain":false,"substitute":true},"offsides":null,"shots":{"total":null,"on":null},"goals":{"total":null,"conceded":0,"assists":null,"saves":null},"passes":{"total":null,"key":null,"accuracy":null},"tackles":{"total":null,"blocks":null,"interceptions":null},"duels":{"total":null,"won":null},"dribbles":{"attempts":null,"success":null,"past":null},"fouls":{"drawn":null,"committed":null},"cards":{"yellow":0,"red":0},"penalty":{"won":null,"commited":null,"scored":0,"missed":0,"saved":null}}]},{"player":{"id":18834,"name":"Andriy Yarmolenko","photo":"https:\/\/media.api-sports.io\/football\/players\/18834.png"},"statistics":[{"games":{"minutes":null,"number":7,"position":"F","rating":null,"captain":false,"substitute":true},"offsides":null,"shots":{"total":null,"on":null},"goals":{"total":null,"conceded":0,"assists":null,"saves":null},"passes":{"total":null,"key":null,"accuracy":null},"tackles":{"total":null,"blocks":null,"interceptions":null},"duels":{"total":null,"won":null},"dribbles":{"attempts":null,"success":null,"past":null},"fouls":{"drawn":null,"committed":null},"cards":{"yellow":0,"red":0},"penalty":{"won":null,"commited":null,"scored":0,"missed":0,"saved":null}}]}]}]}