{"get":"fixtures\/players","parameters":{"fixture":"710762"},"errors":[],"results":2,"paging":{"current":1,"total":1},"response":[{"team":{"id":46,"name":"Leicester","logo":"https:\/\/media.api-sports.io\/football\/teams\/46.png","update":"2022-05-24T04:12:46+00:00"},"players":[{"player":{"id":2728,"name":"Kasper Schmeichel","photo":"https:\/\/media.api-sports.io\/football\/players\/2728.png"},"statistics":[{"games":{"minutes":90,"number":1,"position":"G","rating":"8.2","captain":true,"substitute":false},"offsides":null,"shots":{"total":null,"on":null},"goals":{"total":null,"conceded":0,"assists":null,"saves":5},"passes":{"total":18,"key":null,"accuracy":"18"},"tackles":{"total":null,"blocks":null,"interceptions":null},"duels":{"total":null,"won":null},"dribbles":{"attempts":null,"success":null,"past":null},"fouls":{"drawn":null,"committed":null},"cards":{"yellow":0,"red":0},"penalty":{"won":null,"commited":null,"scored":0,"missed":0,"saved":0}}]},{"player":{"id":2920,"name":"Timothy Castagne","photo":"https:\/\/media.api-sports.io\/football\/players\/2920.png"},"statistics":[{"games":{"minutes":90,"number":27,"position":"D","rating":"7.7","captain":false,"substitute":false},"offsides":null,"shots":{"total":null,"on":null},"goals":{"total":null,"conceded":0,"assists":null,"saves":null},"passes":{"total":65,"key":2,"accuracy":"60"},"tackles":{"total":5,"blocks":null,"interceptions":null},"duels":{"total":7,"won":5},"dribbles":{"attempts":1,"success":null,"past":1},"fouls":{"drawn":null,"committed":null},"cards":{"yellow":0,"red":0},"penalty":{"won":null,"commited":null,"scored":0,"missed":0,"saved":null}}]},{"player":{"id":3421,"name":"Daniel Amartey","photo":"https:\/\/media.api-sports.io\/football\/players\/3421.png"},"statistics":[{"games":{"minutes":90,"number":18,"position":"D","rating":"7","captain":false,"substitute":false},"offsides":null,"shots":{"total":null,"on":null},"goals":{"total":null,"conceded":0,"assists":null,"saves":null},"passes":{"total":94,"key":null,"accuracy":"84"},"tackles":{"total":null,"blocks":null,"interceptions":null},"duels":{"total":6,"won":5},"dribbles":{"attempts":1,"success":1,"past":1},"fouls":{"drawn":null,"committed":null},"cards":{"yellow":0,"red":0},"penalty":{"won":null,"commited":null,"scored":0,"missed":0,"saved":null}}]},{"player":{"id":18772,"name":"Jonny Evans","photo":"https:\/\/media.api-sports.io\/football\/players\/18772.png"},"statistics":[{"games":{"minutes":90,"number":6,"position":"D","rating":"7.3","captain":false,"substitute":false},"offsides":null,"shots":{"total":null,"on":null},"goals":{"total":null,"conceded":0,"assists":null,"saves":null},"passes":{"total":95,"key":null,"accuracy":"85"},"tackles":{"total":null,"blocks":null,"interceptions":1},"duels":{"total":4,"won":3},"dribbles":{"attempts":null,"success":null,"past":1},"fouls":{"drawn":null,"committed":null},"cards":{"yellow":0,"red":0},"penalty":{"won":null,"commited":null,"scored":0,"missed":0,"saved":null}}]},{"player":{"id":19760,"name":"James Justin","photo":"https:\/\/media.api-sports.io\/football\/players\/19760.png"},"statistics":[{"games":{"minutes":90,"number":2,"position":"D","rating":"7.5","captain":false,"substitute":false},"offsides":null,"shots":{"total":null,"on":null},"goals":{"total":null,"conceded":0,"assists":null,"saves":null},"passes":{"total":71,"key":2,"accuracy":"63"},"tackles":{"total":2,"blocks":null,"interceptions":1},"duels":{"total":11,"won":7},"dribbles":{"attempts":3,"success":2,"past":1},"fouls":{"drawn":null,"committed":null},"cards":{"yellow":0,"red":0},"penalty":{"won":null,"commited":null,"scored":0,"missed":0,"saved":null}}]},{"player":{"id":2926,"name":"Youri Tielemans","photo":"https:\/\/media.api-sports.io\/football\/players\/2926.png"},"statistics":[{"games":{"minutes":90,"number":8,"position":"M","rating":"7.9","captain":false,"substitute":false},"offsides":null,"shots":{"total":1,"on":null},"goals":{"total":null,"conceded":0,"assists":null,"saves":null},"passes":{"total":92,"key":2,"accuracy":"84"},"tackles":{"total":5,"blocks":null,"interceptions":1},"duels":{"total":14,"won":8},"dribbles":{"attempts":4,"success":1,"past":null},"fouls":{"drawn":null,"committed":2},"cards":{"yellow":0,"red":0},"penalty":{"won":null,"commited":null,"scored":0,"missed":0,"saved":null}}]},{"player":{"id":148099,"name":"Kiernan Dewsbury-Hall","photo":"https:\/\/media.api-sports.io\/football\/players\/148099.png"},"statistics":[{"games":{"minutes":90,"number":22,"position":"M","rating":"7.3","captain":false,"substitute":false},"offsides":null,"shots":{"total":null,"on":null},"goals":{"total":null,"conceded":0,"assists":null,"saves":null},"passes":{"total":59,"key":3,"accuracy":"53"},"tackles":{"total":null,"blocks":null,"interceptions":null},"duels":{"total":8,"won":4},"dribbles":{"attempts":3,"success":2,"past":null},"fouls":{"drawn":1,"committed":1},"cards":{"yellow":0,"red":0},"penalty":{"won":null,"commited":null,"scored":0,"missed":0,"saved":null}}]},{"player":{"id":18767,"name":"Ademola Lookman","photo":"https:\/\/media.api-sports.io\/football\/players\/18767.png"},"statistics":[{"games":{"minutes":45,"number":37,"position":"M","rating":"6.2","captain":false,"substitute":false},"offsides":1,"shots":{"total":1,"on":1},"goals":{"total":null,"conceded":0,"assists":null,"saves":null},"passes":{"total":28,"key":1,"accuracy":"24"},"tackles":{"total":1,"blocks":null,"interceptions":null},"duels":{"total":8,"won":2},"dribbles":{"attempts":null,"success":null,"past":1},"fouls":{"drawn":1,"committed":2},"cards":{"yellow":0,"red":0},"penalty":{"won":null,"commited":null,"scored":0,"missed":0,"saved":null}}]},{"player":{"id":18784,"name":"James Maddison","photo":"https:\/\/media.api-sports.io\/football\/players\/18784.png"},"statistics":[{"games":{"minutes":90,"number":10,"position":"M","rating":"8.3","captain":false,"substitute":false},"offsides":null,"shots":{"total":3,"on":3},"goals":{"total":1,"conceded":0,"assists":null,"saves":null},"passes":{"total":40,"key":2,"accuracy":"35"},"tackles":{"total":6,"blocks":null,"interceptions":null},"duels":{"total":17,"won":11},"dribbles":{"attempts":5,"success":2,"past":null},"fouls":{"drawn":3,"committed":2},"cards":{"yellow":0,"red":0},"penalty":{"won":null,"commited":null,"scored":0,"missed":0,"saved":null}}]},{"player":{"id":18778,"name":"Harvey Barnes","photo":"https:\/\/media.api-sports.io\/football\/players\/18778.png"},"statistics":[{"games":{"minutes":90,"number":7,"position":"M","rating":"7.5","captain":false,"substitute":false},"offsides":null,"shots":{"total":2,"on":null},"goals":{"total":null,"conceded":0,"assists":2,"saves":null},"passes":{"total":34,"key":2,"accuracy":"27"},"tackles":{"total":3,"blocks":null,"interceptions":null},"duels":{"total":14,"won":5},"dribbles":{"attempts":3,"success":1,"past":3},"fouls":{"drawn":null,"committed":2},"cards":{"yellow":0,"red":0},"penalty":{"won":null,"commited":null,"scored":0,"missed":0,"saved":null}}]},{"player":{"id":18788,"name":"Jamie Vardy","photo":"https:\/\/media.api-sports.io\/football\/players\/18788.png"},"statistics":[{"games":{"minutes":90,"number":9,"position":"F","rating":"8.2","captain":false,"substitute":false},"offsides":null,"shots":{"total":6,"on":4},"goals":{"total":2,"conceded":0,"assists":null,"saves":null},"passes":{"total":9,"key":null,"accuracy":"6"},"tackles":{"total":2,"blocks":null,"interceptions":null},"duels":{"total":6,"won":3},"dribbles":{"attempts":1,"success":null,"past":null},"fouls":{"drawn":null,"committed":1},"cards":{"yellow":0,"red":0},"penalty":{"won":null,"commited":null,"scored":0,"missed":0,"saved":null}}]},{"player":{"id":18146,"name":"Danny Ward","photo":"https:\/\/media.api-sports.io\/football\/players\/18146.png"},"statistics":[{"games":{"minutes":null,"number":12,"position":"G","rating":null,"captain":false,"substitute":true},"offsides":null,"shots":{"total":null,"on":null},"goals":{"total":null,"conceded":0,"assists":null,"saves":null},"passes":{"total":null,"key":null,"accuracy":null},"tackles":{"total":null,"blocks":null,"interceptions":null},"duels":{"total":null,"won":null},"dribbles":{"attempts":null,"success":null,"past":null},"fouls":{"drawn":null,"committed":null},"cards":{"yellow":0,"red":0},"penalty":{"won":null,"commited":null,"scored":0,"missed":0,"saved":null}}]},{"player":{"id":152969,"name":"Luke Thomas","photo":"https:\/\/media.api-sports.io\/football\/players\/152969.png"},"statistics":[{"games":{"minutes":null,"number":33,"position":"D","rating":null,"captain":false,"substitute":true},"offsides":null,"shots":{"total":null,"on":null},"goals":{"total":null,"conceded":0,"assists":null,"saves":null},"passes":{"total":null,"key":null,"accuracy":null},"tackles":{"total":null,"blocks":null,"interceptions":null},"duels":{"total":null,"won":null},"dribbles":{"attempts":null,"success":null,"past":null},"fouls":{"drawn":null,"committed":null},"cards":{"yellow":0,"red":0},"penalty":{"won":null,"commited":null,"scored":0,"missed":0,"saved":null}}]},{"player":{"id":18776,"name":"\u00c7a\u011flar S\u00f6y\u00fcnc\u00fc","photo":"https:\/\/media.api-sports.io\/football\/players\/18776.png"},"statistics":[{"games":{"minutes":null,"number":4,"position":"D","rating":null,"captain":false,"substitute":true},"offsides":null,"shots":{"total":null,"on":null},"goals":{"total":null,"conceded":0,"assists":null,"saves":null},"passes":{"total":null,"key":null,"accuracy":null},"tackles":{"total":null,"blocks":null,"interceptions":null},"duels":{"total":null,"won":null},"dribbles":{"attempts":null,"success":null,"past":null},"fouls":{"drawn":null,"committed":null},"cards":{"yellow":0,"red":0},"penalty":{"won":null,"commited":null,"scored":0,"missed":0,"saved":null}}]},{"player":{"id":18785,"name":"Nampalys Mendy","photo":"https:\/\/media.api-sports.io\/football\/players\/18785.png"},"statistics":[{"games":{"minutes":45,"number":24,"position":"M","rating":"6.6","captain":false,"substitute":true},"offsides":null,"shots":{"total":null,"on":null},"goals":{"total":null,"conceded":0,"assists":null,"saves":null},"passes":{"total":35,"key":null,"accuracy":"34"},"tackles":{"total":null,"blocks":null,"interceptions":1},"duels":{"total":null,"won":null},"dribbles":{"attempts":null,"success":null,"past":null},"fouls":{"drawn":null,"committed":null},"cards":{"yellow":0,"red":0},"penalty":{"won":null,"commited":null,"scored":0,"missed":0,"saved":null}}]},{"player":{"id":18777,"name":"Marc Albrighton","photo":"https:\/\/media.api-sports.io\/football\/players\/18777.png"},"statistics":[{"games":{"minutes":null,"number":11,"position":"M","rating":null,"captain":false,"substitute":true},"offsides":null,"shots":{"total":null,"on":null},"goals":{"total":null,"conceded":0,"assists":null,"saves":null},"passes":{"total":null,"key":null,"accuracy":null},"tackles":{"total":null,"blocks":null,"interceptions":null},"duels":{"total":null,"won":null},"dribbles":{"attempts":null,"success":null,"past":null},"fouls":{"drawn":null,"committed":null},"cards":{"yellow":0,"red":0},"penalty":{"won":null,"commited":null,"scored":0,"missed":0,"saved":null}}]},{"player":{"id":1098,"name":"Patson Daka","photo":"https:\/\/media.api-sports.io\/football\/players\/1098.png"},"statistics":[{"games":{"minutes":null,"number":29,"position":"F","rating":null,"captain":false,"substitute":true},"offsides":null,"shots":{"total":null,"on":null},"goals":{"total":null,"conceded":0,"assists":null,"saves":null},"passes":{"total":null,"key":null,"accuracy":null},"tackles":{"total":null,"blocks":null,"interceptions":null},"duels":{"total":null,"won":null},"dribbles":{"attempts":null,"success":null,"past":null},"fouls":{"drawn":null,"committed":null},"cards":{"yellow":0,"red":0},"penalty":{"won":null,"commited":null,"scored":0,"missed":0,"saved":null}}]},{"player":{"id":18906,"name":"Ayoze P\u00e9rez","photo":"https:\/\/media.api-sports.io\/football\/players\/18906.png"},"statistics":[{"games":{"minutes":null,"number":17,"position":"F","rating":null,"captain":false,"substitute":true},"offsides":null,"shots":{"total":null,"on":null},"goals":{"total":null,"conceded":0,"assists":null,"saves":null},"passes":{"total":null,"key":null,"accuracy":null},"tackles":{"total":null,"blocks":null,"interceptions":null},"duels":{"total":null,"won":null},"dribbles":{"attempts":null,"success":null,"past":null},"fouls":{"drawn":null,"committed":null},"cards":{"yellow":0,"red":0},"penalty":{"won":null,"commited":null,"scored":0,"missed":0,"saved":null}}]},{"player":{"id":2778,"name":"Kelechi Iheanacho","photo":"https:\/\/media.api-sports.io\/football\/players\/2778.png"},"statistics":[{"games":{"minutes":null,"number":14,"position":"F","rating":null,"captain":false,"substitute":true},"offsides":null,"shots":{"total":null,"on":null},"goals":{"total":null,"conceded":0,"assists":null,"saves":null},"passes":{"total":null,"key":null,"accuracy":null},"tackles":{"total":null,"blocks":null,"interceptions":null},"duels":{"total":null,"won":null},"dribbles":{"attempts":null,"success":null,"past":null},"fouls":{"drawn":null,"committed":null},"cards":{"yellow":0,"red":0},"penalty":{"won":null,"commited":null,"scored":0,"missed":0,"saved":null}}]}]},{"team":{"id":71,"name":"Norwich","logo":"https:\/\/media.api-sports.io\/football\/teams\/71.png","update":"2022-05-24T04:12:47+00:00"},"players":[{"player":{"id":18933,"name":"Angus Gunn","photo":"https:\/\/media.api-sports.io\/football\/players\/18933.png"},"statistics":[{"games":{"minutes":90,"number":28,"position":"G","rating":"6.9","captain":false,"substitute":false},"offsides":null,"shots":{"total":null,"on":null},"goals":{"total":null,"conceded":3,"assists":null,"saves":5},"passes":{"total":33,"key":null,"accuracy":"17"},"tackles":{"total":null,"blocks":null,"interceptions":null},"duels":{"total":null,"won":null},"dribbles":{"attempts":null,"success":null,"past":null},"fouls":{"drawn":null,"committed":null},"cards":{"yellow":0,"red":0},"penalty":{"won":null,"commited":null,"scored":0,"missed":0,"saved":0}}]},{"player":{"id":19070,"name":"Max Aarons","photo":"https:\/\/media.api-sports.io\/football\/players\/19070.png"},"statistics":[{"games":{"minutes":90,"number":2,"position":"D","rating":"6.7","captain":false,"substitute":false},"offsides":null,"shots":{"total":null,"on":null},"goals":{"total":null,"conceded":0,"assists":null,"saves":null},"passes":{"total":35,"key":1,"accuracy":"28"},"tackles":{"total":3,"blocks":null,"interceptions":1},"duels":{"total":8,"won":5},"dribbles":{"attempts":3,"success":1,"past":null},"fouls":{"drawn":1,"committed":null},"cards":{"yellow":0,"red":0},"penalty":{"won":null,"commited":null,"scored":0,"missed":0,"saved":null}}]},{"player":{"id":19066,"name":"Grant Hanley","photo":"https:\/\/media.api-sports.io\/football\/players\/19066.png"},"statistics":[{"games":{"minutes":90,"number":5,"position":"D","rating":"7.3","captain":true,"substitute":false},"offsides":null,"shots":{"total":1,"on":1},"goals":{"total":null,"conceded":0,"assists":null,"saves":null},"passes":{"total":27,"key":1,"accuracy":"23"},"tackles":{"total":1,"blocks":3,"interceptions":null},"duels":{"total":4,"won":4},"dribbles":{"attempts":null,"success":null,"past":null},"fouls":{"drawn":1,"committed":null},"cards":{"yellow":0,"red":0},"penalty":{"won":null,"commited":null,"scored":0,"missed":0,"saved":null}}]},{"player":{"id":19287,"name":"Sam Byram","photo":"https:\/\/media.api-sports.io\/football\/players\/19287.png"},"statistics":[{"games":{"minutes":90,"number":3,"position":"D","rating":"6.3","captain":false,"substitute":false},"offsides":null,"shots":{"total":1,"on":null},"goals":{"total":null,"conceded":0,"assists":null,"saves":null},"passes":{"total":34,"key":null,"accuracy":"31"},"tackles":{"total":null,"blocks":null,"interceptions":null},"duels":{"total":6,"won":2},"dribbles":{"attempts":null,"success":null,"past":null},"fouls":{"drawn":1,"committed":null},"cards":{"yellow":0,"red":0},"penalty":{"won":null,"commited":null,"scored":0,"missed":0,"saved":null}}]},{"player":{"id":2360,"name":"Dimitrios Giannoulis","photo":"https:\/\/media.api-sports.io\/football\/players\/2360.png"},"statistics":[{"games":{"minutes":90,"number":30,"position":"D","rating":"6.7","captain":false,"substitute":false},"offsides":null,"shots":{"total":1,"on":1},"goals":{"total":null,"conceded":0,"assists":null,"saves":null},"passes":{"total":45,"key":null,"accuracy":"40"},"tackles":{"total":5,"blocks":null,"interceptions":2},"duels":{"total":16,"won":8},"dribbles":{"attempts":4,"success":1,"past":2},"fouls":{"drawn":2,"committed":1},"cards":{"yellow":0,"red":0},"penalty":{"won":null,"commited":null,"scored":0,"missed":0,"saved":null}}]},{"player":{"id":22170,"name":"Pierre Lees Melou","photo":"https:\/\/media.api-sports.io\/football\/players\/22170.png"},"statistics":[{"games":{"minutes":90,"number":20,"position":"M","rating":"6.9","captain":false,"substitute":false},"offsides":null,"shots":{"total":null,"on":null},"goals":{"total":null,"conceded":0,"assists":null,"saves":null},"passes":{"total":41,"key":null,"accuracy":"38"},"tackles":{"total":2,"blocks":2,"interceptions":2},"duels":{"total":6,"won":2},"dribbles":{"attempts":null,"success":null,"past":2},"fouls":{"drawn":null,"committed":2},"cards":{"yellow":0,"red":0},"penalty":{"won":null,"commited":null,"scored":0,"missed":0,"saved":null}}]},{"player":{"id":278064,"name":"Tony Springett","photo":"https:\/\/media.api-sports.io\/football\/players\/278064.png"},"statistics":[{"games":{"minutes":67,"number":45,"position":"M","rating":"6.7","captain":false,"substitute":false},"offsides":null,"shots":{"total":1,"on":1},"goals":{"total":null,"conceded":0,"assists":null,"saves":null},"passes":{"total":19,"key":2,"accuracy":"12"},"tackles":{"total":2,"blocks":null,"interceptions":null},"duels":{"total":12,"won":5},"dribbles":{"attempts":2,"success":1,"past":2},"fouls":{"drawn":1,"committed":null},"cards":{"yellow":0,"red":0},"penalty":{"won":null,"commited":null,"scored":0,"missed":0,"saved":null}}]},{"player":{"id":720,"name":"Lukas Rupp","photo":"https:\/\/media.api-sports.io\/football\/players\/720.png"},"statistics":[{"games":{"minutes":58,"number":7,"position":"M","rating":"6.3","captain":false,"substitute":false},"offsides":null,"shots":{"total":null,"on":null},"goals":{"total":null,"conceded":0,"assists":null,"saves":null},"passes":{"total":19,"key":null,"accuracy":"14"},"tackles":{"total":1,"blocks":null,"interceptions":null},"duels":{"total":9,"won":5},"dribbles":{"attempts":5,"success":3,"past":1},"fouls":{"drawn":null,"committed":null},"cards":{"yellow":0,"red":0},"penalty":{"won":null,"commited":null,"scored":0,"missed":0,"saved":null}}]},{"player":{"id":130423,"name":"Billy Gilmour","photo":"https:\/\/media.api-sports.io\/football\/players\/130423.png"},"statistics":[{"games":{"minutes":90,"number":8,"position":"M","rating":"7.2","captain":false,"substitute":false},"offsides":null,"shots":{"total":3,"on":1},"goals":{"total":null,"conceded":0,"assists":null,"saves":null},"passes":{"total":48,"key":1,"accuracy":"41"},"tackles":{"total":3,"blocks":1,"interceptions":null},"duels":{"total":12,"won":5},"dribbles":{"attempts":2,"success":null,"past":1},"fouls":{"drawn":2,"committed":2},"cards":{"yellow":0,"red":0},"penalty":{"won":null,"commited":null,"scored":0,"missed":0,"saved":null}}]},{"player":{"id":25324,"name":"Milot Rashica","photo":"https:\/\/media.api-sports.io\/football\/players\/25324.png"},"statistics":[{"games":{"minutes":67,"number":17,"position":"M","rating":"6.3","captain":false,"substitute":false},"offsides":null,"shots":{"total":null,"on":null},"goals":{"total":null,"conceded":0,"assists":null,"saves":null},"passes":{"total":15,"key":1,"accuracy":"13"},"tackles":{"total":1,"blocks":1,"interceptions":null},"duels":{"total":7,"won":2},"dribbles":{"attempts":1,"success":null,"past":null},"fouls":{"drawn":1,"committed":null},"cards":{"yellow":0,"red":0},"penalty":{"won":null,"commited":null,"scored":0,"missed":0,"saved":null}}]},{"player":{"id":19085,"name":"Teemu Pukki","photo":"https:\/\/media.api-sports.io\/football\/players\/19085.png"},"statistics":[{"games":{"minutes":90,"number":22,"position":"F","rating":"6.2","captain":false,"substitute":false},"offsides":null,"shots":{"total":2,"on":1},"goals":{"total":null,"conceded":0,"assists":null,"saves":null},"passes":{"total":22,"key":1,"accuracy":"17"},"tackles":{"total":null,"blocks":null,"interceptions":null},"duels":{"total":10,"won":1},"dribbles":{"attempts":2,"success":1,"past":1},"fouls":{"drawn":null,"committed":null},"cards":{"yellow":0,"red":0},"penalty":{"won":null,"commited":null,"scored":0,"missed":0,"saved":null}}]},{"player":{"id":19061,"name":"Tim Krul","photo":"https:\/\/media.api-sports.io\/football\/players\/19061.png"},"statistics":[{"games":{"minutes":null,"number":1,"position":"G","rating":null,"captain":false,"substitute":true},"offsides":null,"shots":{"total":null,"on":null},"goals":{"total":null,"conceded":0,"assists":null,"saves":null},"passes":{"total":null,"key":null,"accuracy":null},"tackles":{"total":null,"blocks":null,"interceptions":null},"duels":{"total":null,"won":null},"dribbles":{"attempts":null,"success":null,"past":null},"fouls":{"drawn":null,"committed":null},"cards":{"yellow":0,"red":0},"penalty":{"won":null,"commited":null,"scored":0,"missed":0,"saved":null}}]},{"player":{"id":18914,"name":"Ben Gibson","photo":"https:\/\/media.api-sports.io\/football\/players\/18914.png"},"statistics":[{"games":{"minutes":null,"number":4,"position":"D","rating":null,"captain":false,"substitute":true},"offsides":null,"shots":{"total":null,"on":null},"goals":{"total":null,"conceded":0,"assists":null,"saves":null},"passes":{"total":null,"key":null,"accuracy":null},"tackles":{"total":null,"blocks":null,"interceptions":null},"duels":{"total":null,"won":null},"dribbles":{"attempts":null,"success":null,"past":null},"fouls":{"drawn":null,"committed":null},"cards":{"yellow":0,"red":0},"penalty":{"won":null,"commited":null,"scored":0,"missed":0,"saved":null}}]},{"player":{"id":138806,"name":"Brandon Williams","photo":"https:\/\/media.api-sports.io\/football\/players\/138806.png"},"statistics":[{"games":{"minutes":null,"number":21,"position":"D","rating":null,"captain":false,"substitute":true},"offsides":null,"shots":{"total":null,"on":null},"goals":{"total":null,"conceded":0,"assists":null,"saves":null},"passes":{"total":null,"key":null,"accuracy":null},"tackles":{"total":null,"blocks":null,"interceptions":null},"duels":{"total":null,"won":null},"dribbles":{"attempts":null,"success":null,"past":null},"fouls":{"drawn":null,"committed":null},"cards":{"yellow":0,"red":0},"penalty":{"won":null,"commited":null,"scored":0,"missed":0,"saved":null}}]},{"player":{"id":19100,"name":"Kieran Dowell","photo":"https:\/\/media.api-sports.io\/football\/players\/19100.png"},"statistics":[{"games":{"minutes":null,"number":10,"position":"M","rating":null,"captain":false,"substitute":true},"offsides":null,"shots":{"total":null,"on":null},"goals":{"total":null,"conceded":0,"assists":null,"saves":null},"passes":{"total":null,"key":null,"accuracy":null},"tackles":{"total":null,"blocks":null,"interceptions":null},"duels":{"total":null,"won":null},"dribbles":{"attempts":null,"success":null,"past":null},"fouls":{"drawn":null,"committed":null},"cards":{"yellow":0,"red":0},"penalty":{"won":null,"commited":null,"scored":0,"missed":0,"saved":null}}]},{"player":{"id":15832,"name":"Jacob Lungi S\u00f8rensen","photo":"https:\/\/media.api-sports.io\/football\/players\/15832.png"},"statistics":[{"games":{"minutes":32,"number":19,"position":"M","rating":"6.2","captain":false,"substitute":true},"offsides":null,"shots":{"total":null,"on":null},"goals":{"total":null,"conceded":0,"assists":null,"saves":null},"passes":{"total":8,"key":null,"accuracy":"6"},"tackles":{"total":null,"blocks":null,"interceptions":null},"duels":{"total":1,"won":null},"dribbles":{"attempts":1,"success":null,"past":null},"fouls":{"drawn":null,"committed":null},"cards":{"yellow":0,"red":0},"penalty":{"won":null,"commited":null,"scored":0,"missed":0,"saved":null}}]},{"player":{"id":40774,"name":"Przemys\u0142aw P\u0142acheta","photo":"https:\/\/media.api-sports.io\/football\/players\/40774.png"},"statistics":[{"games":{"minutes":23,"number":11,"position":"M","rating":"6.3","captain":false,"substitute":true},"offsides":null,"shots":{"total":null,"on":null},"goals":{"total":null,"conceded":0,"assists":null,"saves":null},"passes":{"total":5,"key":null,"accuracy":"3"},"tackles":{"total":null,"blocks":null,"interceptions":null},"duels":{"total":1,"won":1},"dribbles":{"attempts":1,"success":1,"past":null},"fouls":{"drawn":null,"committed":null},"cards":{"yellow":0,"red":0},"penalty":{"won":null,"commited":null,"scored":0,"missed":0,"saved":null}}]},{"player":{"id":171034,"name":"Liam Gibbs","photo":"https:\/\/media.api-sports.io\/football\/players\/171034.png"},"statistics":[{"games":{"minutes":null,"number":42,"position":"M","rating":null,"captain":false,"substitute":true},"offsides":null,"shots":{"total":null,"on":null},"goals":{"total":null,"conceded":0,"assists":null,"saves":null},"passes":{"total":null,"key":null,"accuracy":null},"tackles":{"total":null,"blocks":null,"interceptions":null},"duels":{"total":null,"won":null},"dribbles":{"attempts":null,"success":null,"past":null},"fouls":{"drawn":null,"committed":null},"cards":{"yellow":0,"red":0},"penalty":{"won":null,"commited":null,"scored":0,"missed":0,"saved":null}}]},{"player":{"id":278095,"name":"Jonathan Rowe","photo":"https:\/\/media.api-sports.io\/football\/players\/278095.png"},"statistics":[{"games":{"minutes":23,"number":46,"position":"F","rating":"6.3","captain":false,"substitute":true},"offsides":null,"shots":{"total":null,"on":null},"goals":{"total":null,"conceded":0,"assists":null,"saves":null},"passes":{"total":3,"key":null,"accuracy":"2"},"tackles":{"total":1,"blocks":null,"interceptions":null},"duels":{"total":3,"won":2},"dribbles":{"attempts":1,"success":null,"past":null},"fouls":{"drawn":1,"committed":null},"cards":{"yellow":0,"red":0},"penalty":{"won":null,"commited":null,"scored":0,"missed":0,"saved":null}}]},{"player":{"id":161800,"name":"Christos Tzolis","photo":"https:\/\/media.api-sports.io\/football\/players\/161800.png"},"statistics":[{"games":{"minutes":null,"number":18,"position":"F","rating":null,"captain":false,"substitute":true},"offsides":null,"shots":{"total":null,"on":null},"goals":{"total":null,"conceded":0,"assists":null,"saves":null},"passes":{"total":null,"key":null,"accuracy":null},"tackles":{"total":null,"blocks":null,"interceptions":null},"duels":{"total":null,"won":null},"dribbles":{"attempts":null,"success":null,"past":null},"fouls":{"drawn":null,"committed":null},"cards":{"yellow":0,"red":0},"penalty":{"won":null,"commited":null,"scored":0,"missed":0,"saved":null}}]}]}]}